yadupe/__init__.py
yadupe/__main__.py
yadupe/argutils.py
yadupe/core.py
yadupe/hashutils.py
yadupe-1.1.0.dist-info/LICENSE
yadupe-1.1.0.dist-info/METADATA
yadupe-1.1.0.dist-info/WHEEL
yadupe-1.1.0.dist-info/entry_points.txt
yadupe-1.1.0.dist-info/top_level.txt
yadupe-1.1.0.dist-info/RECORD
