Metadata-Version: 2.1
Name: yadupe
Version: 1.1.0
Summary: Recursively scan one or more given directories for duplicate files.
Home-page: https://github.com/yugn/yadupe
Author: yugn
Author-email: cbznysrnpu@gmail.com
License: MIT
Platform: UNKNOWN
Classifier: License :: OSI Approved :: MIT License
Classifier: Programming Language :: Python :: 3
Classifier: Programming Language :: Python :: 3.6
Classifier: Environment :: Console
Classifier: Operating System :: POSIX :: Linux
Classifier: Operating System :: Microsoft :: Windows
License-File: LICENSE
Requires-Dist: tqdm
